corona/__init__.py
corona/__main__.py
corona/setup.py
corona/snap.py
corona-0.1.2.dist-info/METADATA
corona-0.1.2.dist-info/WHEEL
corona-0.1.2.dist-info/entry_points.txt
corona-0.1.2.dist-info/top_level.txt
corona-0.1.2.dist-info/RECORD
