Metadata-Version: 2.1
Name: corona
Version: 0.1.2
Summary: Website Screenshot Utility
Home-page: https://github.com/pyarmory/corona
Author: John Vrbanac
Author-email: john.vrbanac@linux.com
License: Apache v2
Keywords: screenshot website
Platform: UNKNOWN
Classifier: Development Status :: 3 - Alpha
Classifier: Intended Audience :: Developers
Classifier: License :: OSI Approved :: Apache Software License
Classifier: Programming Language :: Python :: 3.7
Requires-Python: >=3.6
Requires-Dist: pyppeteer (==0.0.25)
